async_patterns/__init__.py
async_patterns/tests/test_basic.py
async_patterns-0.2.dist-info/DESCRIPTION.rst
async_patterns-0.2.dist-info/METADATA
async_patterns-0.2.dist-info/RECORD
async_patterns-0.2.dist-info/WHEEL
async_patterns-0.2.dist-info/metadata.json
async_patterns-0.2.dist-info/top_level.txt
