Metadata-Version: 2.0
Name: async-patterns
Version: 0.2
Summary: pattern for registering callbacks
Home-page: http://github.com/chuck1/ws-callbacks
Author: Charles Rymal
Author-email: charlesrymal@gmail.com
License: MIT
Platform: UNKNOWN
Requires-Dist: Babel (==2.4.0)
Requires-Dist: Jinja2 (==2.9.6)
Requires-Dist: MarkupSafe (==1.0)
Requires-Dist: Pygments (==2.2.0)
Requires-Dist: Sphinx (==1.6.2)
Requires-Dist: aiobotocore (==0.4.1)
Requires-Dist: aiohttp (==2.2.0)
Requires-Dist: alabaster (==0.7.10)
Requires-Dist: appdirs (==1.4.3)
Requires-Dist: async-timeout (==1.2.1)
Requires-Dist: botocore (==1.5.70)
Requires-Dist: certifi (==2017.4.17)
Requires-Dist: chardet (==3.0.4)
Requires-Dist: docutils (==0.13.1)
Requires-Dist: fs (==2.0.4)
Requires-Dist: idna (==2.5)
Requires-Dist: imagesize (==0.7.1)
Requires-Dist: jmespath (==0.9.3)
Requires-Dist: multidict (==3.1.0)
Requires-Dist: numpy (==1.13.0)
Requires-Dist: oauthlib (==2.0.2)
Requires-Dist: packaging (==16.8)
Requires-Dist: pkgtool (==0.1b52)
Requires-Dist: py (==1.4.34)
Requires-Dist: pyparsing (==2.2.0)
Requires-Dist: pytest (==3.1.2)
Requires-Dist: python-dateutil (==2.6.0)
Requires-Dist: pytz (==2017.2)
Requires-Dist: requests (==2.18.1)
Requires-Dist: requests-oauthlib (==0.8.0)
Requires-Dist: six (==1.10.0)
Requires-Dist: snowballstemmer (==1.2.1)
Requires-Dist: sphinxcontrib-websupport (==1.0.1)
Requires-Dist: termcolor (==1.1.0)
Requires-Dist: toml (==0.9.2)
Requires-Dist: urllib3 (==1.21.1)
Requires-Dist: wrapt (==1.10.10)
Requires-Dist: yarl (==0.10.3)
